{"data":[{"name":"维多利亚的秘密：泳装特辑2015.特效中字.The.Victorias.Secret.Swim.Special.2015.HD1080P.X264.AAC.English.CHS.Mp4Ba","mag":"magnet:?xt=urn:btih:aa0022b9d9be7f0bf71c364b6787f72981d814d6&tr=http://bt.mp4ba.com:2710/announce"},{"name":"维多利亚的秘密：泳装特辑2015.特效中字.The.Victorias.Secret.Swim.Special.2015.HD720P.X264.AAC.English.CHS.Mp4Ba","mag":"magnet:?xt=urn:btih:5d6ca451346edd929a3eeb4667a1cbfff4455412&tr=http://bt.mp4ba.com:2710/announce"},{"name":"匆匆那年.Fleet.of.Time.2014.HD720P.X264.AAC.Mandarin.CHS-ENG.Mp4Ba","mag":"magnet:?xt=urn:btih:f55ea5d9da9fe67d9d4b348b2b1f4dbf0119b407&tr=http://bt.mp4ba.com:2710/announce"},{"name":"行尸走肉.第五季.The.Walking.Dead.S05E12.2014.HD720P.X264.AAC.English.CHS-ENG.Mp4Ba","mag":"magnet:?xt=urn:btih:95d5e029059a1809622ab8f709c8c51e97b0ca8f&tr=http://bt.mp4ba.com:2710/announce"},{"name":"行尸走肉.第五季.The.Walking.Dead.S05E12.2014.HD1080P.X264.AAC.English.CHS-ENG.Mp4Ba","mag":"magnet:?xt=urn:btih:dab7ea67961ba83358256fbd3aba16ca37ee0a4f&tr=http://bt.mp4ba.com:2710/announce"},{"name":"吉米的舞厅.Jimmys.Hall.2014.BD720P.X264.AAC.English.CHS-ENG.Mp4Ba","mag":"magnet:?xt=urn:btih:ccc595a39f0f16073ed295a9561ea24973e6c29a&tr=http://bt.mp4ba.com:2710/announce"},{"name":"封神英雄榜2.未删减版.Ep21-22.2015.HD1080P.X264.AAC.Mandarin.CHS.Mp4Ba","mag":"magnet:?xt=urn:btih:ab53c5437c2f5705c59feeed069d18c7e747a775&tr=http://bt.mp4ba.com:2710/announce"},{"name":"封神英雄榜2.未删减版.Ep21-22.2015.HD720P.X264.AAC.Mandarin.CHS.Mp4Ba","mag":"magnet:?xt=urn:btih:9df325b9ae79c9cff469a0a0dae6b4b253144136&tr=http://bt.mp4ba.com:2710/announce"},{"name":"赛琳娜.Serena.2014.BD720P.X264.AAC.English.CHS-ENG.Mp4Ba","mag":"magnet:?xt=urn:btih:8f5aa358e9542ec7c2d4564224bbc67e04e12fbc&tr=http://bt.mp4ba.com:2710/announce"},{"name":"赛琳娜.Serena.2014.BD1080P.X264.AAC.English.CHS-ENG.Mp4Ba","mag":"magnet:?xt=urn:btih:ab1c93922e080981c90c85096bda6a01f40e22f6&tr=http://bt.mp4ba.com:2710/announce"},{"name":"柴静雾霾调查：穹顶之下.2015.HD720P.X264.AAC.Mandarin.CHS.Mp4Ba","mag":"magnet:?xt=urn:btih:3cda7a304604445bc9171570406ab86e29a2a8a2&tr=http://bt.mp4ba.com:2710/announce"},{"name":"奔跑吧！兄弟.Running.Man.2015.HD720P.X264.AAC.Mandarin.CHS-ENG.Mp4Ba","mag":"magnet:?xt=urn:btih:2d6cad0e5bdf305c499401a20e6932f4800606c8&tr=http://bt.mp4ba.com:2710/announce"},{"name":"永远十六岁.Laggies.2014.BD720P.X264.AAC.English.CHS-ENG.Mp4Ba","mag":"magnet:?xt=urn:btih:1376c875e5c9344fb5d4efdc3c18b3f2ffde3983&tr=http://bt.mp4ba.com:2710/announce"},{"name":"永远十六岁.Laggies.2014.BD1080P.X264.AAC.English.CHS-ENG.Mp4Ba","mag":"magnet:?xt=urn:btih:7c6bb664d8ef05a9c4e8c4cfba7332fcf59c4e7e&tr=http://bt.mp4ba.com:2710/announce"},{"name":"超能陆战队.Big.Hero.6.2014.HD720P.X264.AAC.English.CHS-ENG.Mp4Ba","mag":"magnet:?xt=urn:btih:e16140cfc7cae85147198cf1971b9c23d638aaee&tr=http://bt.mp4ba.com:2710/announce"},{"name":"超能陆战队.Big.Hero.6.2014.BD1080P.X264.AAC.English.CHS-ENG.Mp4Ba","mag":"magnet:?xt=urn:btih:802a40e13fc594868c4b61d624947704840fbc25&tr=http://bt.mp4ba.com:2710/announce"},{"name":"封神英雄榜2.未删减版.Ep19-20.2015.HD1080P.X264.AAC.Mandarin.CHS.Mp4Ba","mag":"magnet:?xt=urn:btih:6b1907dbe1fbd8efa61c350aa82a4ff483c0782b&tr=http://bt.mp4ba.com:2710/announce"},{"name":"封神英雄榜2.未删减版.Ep19-20.2015.HD720P.X264.AAC.Mandarin.CHS.Mp4Ba","mag":"magnet:?xt=urn:btih:aa21feee78e60fde895456337d855ba34d6b38d2&tr=http://bt.mp4ba.com:2710/announce"},{"name":"博物馆奇妙夜3：墓葬秘密.Night.at.the.Museum.Secret.of.the.Tomb.2014.BD720P.X264.AAC.English.CHS-ENG.Mp4Ba","mag":"magnet:?xt=urn:btih:b959f2fd5001b1e20ea103293c24defe17c10023&tr=http://bt.mp4ba.com:2710/announce"},{"name":"博物馆奇妙夜3：墓葬秘密.Night.at.the.Museum.Secret.of.the.Tomb.2014.BD1080P.X264.AAC.English.CHS-ENG.Mp4Ba","mag":"magnet:?xt=urn:btih:6f3553562ba0778c0f772194740d9725975cfc95&tr=http://bt.mp4ba.com:2710/announce"},{"name":"封神英雄榜2.未删减版.Ep17-18.2015.HD1080P.X264.AAC.Mandarin.CHS.Mp4Ba","mag":"magnet:?xt=urn:btih:cdc87691150368a6cac7e3959cb880b5e7db17e3&tr=http://bt.mp4ba.com:2710/announce"},{"name":"封神英雄榜2.未删减版.Ep17-18.2015.HD720P.X264.AAC.Mandarin.CHS.Mp4Ba","mag":"magnet:?xt=urn:btih:910fb2771741deab66c93f5efacd1bc35dd996fc&tr=http://bt.mp4ba.com:2710/announce"},{"name":"背负春天.特效中字.Climbing.to.Spring.2014.BD1080P.X264.AAC.Japanese.CHS.Mp4Ba","mag":"magnet:?xt=urn:btih:524f59128a688a8a1be3b4c264005f2735ee0769&tr=http://bt.mp4ba.com:2710/announce"},{"name":"背负春天.特效中字.Climbing.to.Spring.2014.BD720P.X264.AAC.Japanese.CHS.Mp4Ba","mag":"magnet:?xt=urn:btih:3bf0041dd1c7f267a83886c6a250bd8063a6d078&tr=http://bt.mp4ba.com:2710/announce"},{"name":"热血男人帮.Hot.Blood.Band.2015.HD720P.X264.AAC.Mandarin.CHS-ENG.Mp4Ba","mag":"magnet:?xt=urn:btih:e31f6327507d87eb42ddf5f220dfedc55080a052&tr=http://bt.mp4ba.com:2710/announce"},{"name":"龙之心3：巫师的诅咒.Dragonheart.3.The.Sorcerers.Curse.2015.BD1080P.X264.AAC.English.CHS-ENG.Mp4Ba","mag":"magnet:?xt=urn:btih:97642ea8a5536e11f7beea5a4172c33bf3a91a74&tr=http://bt.mp4ba.com:2710/announce"},{"name":"龙之心3：巫师的诅咒.Dragonheart.3.The.Sorcerers.Curse.2015.BD720P.X264.AAC.English.CHS-ENG.Mp4Ba","mag":"magnet:?xt=urn:btih:1e74e37cff30c3cadbca7c478e75b12c02b68f93&tr=http://bt.mp4ba.com:2710/announce"},{"name":"哭泣的男人.No.Tears.for.the.Dead.2014.BD1080P.X264.AAC.Korean.CHS.Mp4Ba","mag":"magnet:?xt=urn:btih:7fb1dea991e92f1321efd624bf62d5dc0705a745&tr=http://bt.mp4ba.com:2710/announce"},{"name":"哭泣的男人.No.Tears.for.the.Dead.2014.BD720P.X264.AAC.Korean.CHS.Mp4Ba","mag":"magnet:?xt=urn:btih:22283ecf785bc9642f305fb0b1c37be4b57d4e82&tr=http://bt.mp4ba.com:2710/announce"},{"name":"封神英雄榜2.未删减版.Ep15-16.2015.HD1080P.X264.AAC.Mandarin.CHS.Mp4Ba","mag":"magnet:?xt=urn:btih:5e6e1f65f7da3446389c3ae0b6cd8f364b9b2843&tr=http://bt.mp4ba.com:2710/announce"},{"name":"封神英雄榜2.未删减版.Ep15-16.2015.HD720P.X264.AAC.Mandarin.CHS.Mp4Ba","mag":"magnet:?xt=urn:btih:809ed7c01c7289dbefade7ac6ab41b60bfc7b15a&tr=http://bt.mp4ba.com:2710/announce"},{"name":"鬼纳特归来.Bhoothnath.Returns.2014.BD1080P.X264.AAC.Hindi.CHS.Mp4Ba","mag":"magnet:?xt=urn:btih:5daf81c6a623929f8162ccf5363eb67eaf28fec1&tr=http://bt.mp4ba.com:2710/announce"},{"name":"鬼纳特归来.Bhoothnath.Returns.2014.BD720P.X264.AAC.Hindi.CHS.Mp4Ba","mag":"magnet:?xt=urn:btih:685fc2b6305c551416403a6143623da3fd154712&tr=http://bt.mp4ba.com:2710/announce"},{"name":"封神英雄榜2.未删减版.Ep13-14.2015.HD1080P.X264.AAC.Mandarin.CHS.Mp4Ba","mag":"magnet:?xt=urn:btih:b848dccc42fd690fc4d35113a958b7e25aa23d64&tr=http://bt.mp4ba.com:2710/announce"},{"name":"封神英雄榜2.未删减版.Ep13-14.2015.HD720P.X264.AAC.Mandarin.CHS.Mp4Ba","mag":"magnet:?xt=urn:btih:4b2d4a61589ec2c6db6bd6453546116473ce7dab&tr=http://bt.mp4ba.com:2710/announce"},{"name":"第87届奥斯卡金像奖颁奖典礼.特效中字.The.87th.Annual.Academy.Awards.2015.HD720P.X264.AAC.English.CHS.Mp4Ba","mag":"magnet:?xt=urn:btih:a2992ebb90ba9bbbc68b99f85b1d2979d098b8fc&tr=http://bt.mp4ba.com:2710/announce"},{"name":"第87届奥斯卡金像奖颁奖典礼.特效中字.The.87th.Annual.Academy.Awards.2015.HD1080P.X264.AAC.English.CHS.Mp4Ba","mag":"magnet:?xt=urn:btih:6f20cb1b891c1f9d44d0431a76461200e601305d&tr=http://bt.mp4ba.com:2710/announce"},{"name":"热血之路.Hot.Road.2014.HD720P.X264.AAC.Japanese.CHS.Mp4Ba","mag":"magnet:?xt=urn:btih:0f38c5fd85305b97f30e0012b585f614a790d1a7&tr=http://bt.mp4ba.com:2710/announce"},{"name":"热血之路.Hot.Road.2014.HD1080P.X264.AAC.Japanese.CHS.Mp4Ba","mag":"magnet:?xt=urn:btih:8bc2b912d699a71e24bae1732c84c3f251059f5a&tr=http://bt.mp4ba.com:2710/announce"},{"name":"封神英雄榜2.未删减版.Ep11-12.2015.HD1080P.X264.AAC.Mandarin.CHS.Mp4Ba","mag":"magnet:?xt=urn:btih:332172b807b1af0da5e46b0ed06c2eeaab13e8d3&tr=http://bt.mp4ba.com:2710/announce"},{"name":"封神英雄榜2.未删减版.Ep11-12.2015.HD720P.X264.AAC.Mandarin.CHS.Mp4Ba","mag":"magnet:?xt=urn:btih:2426160325cc5c4d5882139a9a5e150f1e091397&tr=http://bt.mp4ba.com:2710/announce"},{"name":"饥饿游戏3：嘲笑鸟（上）.修复中英字幕.The.Hunger.Games.Mockingjay.Part.1.2014.BD720P.X264.AAC.English.CHS-ENG.Mp4Ba","mag":"magnet:?xt=urn:btih:2047f0a44da056492a497bb0bbb3d4b7daeecc78&tr=http://bt.mp4ba.com:2710/announce"},{"name":"饥饿游戏3：嘲笑鸟（上）.修复中英字幕.The.Hunger.Games.Mockingjay.Part.1.2014.BD1080P.X264.AAC.English.CHS-ENG.Mp4Ba","mag":"magnet:?xt=urn:btih:387bb5d05b02076e5e0cbd7443b83ba3eb965e9a&tr=http://bt.mp4ba.com:2710/announce"},{"name":"封神英雄榜2.未删减版.Ep01-10.2015.HD1080P.X264.AAC.Mandarin.CHS.Mp4Ba","mag":"magnet:?xt=urn:btih:ebe5defbcd1bcae296d96fc7b324e759fcde8b9e&tr=http://bt.mp4ba.com:2710/announce"},{"name":"封神英雄榜2.未删减版.Ep01-10.2015.HD720P.X264.AAC.Mandarin.CHS.Mp4Ba","mag":"magnet:?xt=urn:btih:35885ae903071af15632a6647e474e4f0524e07c&tr=http://bt.mp4ba.com:2710/announce"},{"name":"行尸走肉.第五季.The.Walking.Dead.S05E11.2014.HD720P.X264.AAC.English.CHS-ENG.Mp4Ba","mag":"magnet:?xt=urn:btih:17e2febba1c8ac41b2a3d1dc9046076ee9aa594d&tr=http://bt.mp4ba.com:2710/announce"},{"name":"行尸走肉.第五季.The.Walking.Dead.S05E11.2014.HD1080P.X264.AAC.English.CHS-ENG.Mp4Ba","mag":"magnet:?xt=urn:btih:eeb3ddf79a24de1c00c6df282d158a4b67b702b7&tr=http://bt.mp4ba.com:2710/announce"},{"name":"大人不及格.Otona.Drop.2014.HD1080P.X264.AAC.Japanese.CHS.Mp4Ba","mag":"magnet:?xt=urn:btih:801010169175dc06a165dab4a5882b4b80bb3f7d&tr=http://bt.mp4ba.com:2710/announce"},{"name":"大人不及格.Otona.Drop.2014.HD720P.X264.AAC.Japanese.CHS.Mp4Ba","mag":"magnet:?xt=urn:btih:9e6c420ad1909b6ba2afc72fb8819623a7f646da&tr=http://bt.mp4ba.com:2710/announce"},{"name":"今天的恋爱.特效中字.Today.Love.2014.HD720P.X264.AAC.Korean.CHS.Mp4Ba","mag":"magnet:?xt=urn:btih:5c30ada8c581d2c3bc3906174419486b6cda369a&tr=http://bt.mp4ba.com:2710/announce"}],"count":50}
